ai_bootstrap/__init__.py
ai_bootstrap/ai_planner.py
ai_bootstrap/main.py
ai_bootstrap/code_generator/__init__.py
ai_bootstrap/code_generator/ai_coder.py
ai_bootstrap/code_generator/file_generator.py
ai_bootstrap/project_builder/__init__.py
ai_bootstrap/project_builder/project_assembler.py
ai_bootstrap/project_builder/structure_planner.py
ai_bootstrap/template_analyzer/__init__.py
ai_bootstrap/template_analyzer/pattern_extractor.py
ai_bootstrap/template_analyzer/template_reader.py
ai_bootstrap/templates/core_langchain/.env.example
ai_bootstrap/templates/core_langchain/.gitignore
ai_bootstrap/templates/core_langchain/README.md.jinja
ai_bootstrap/templates/core_langchain/app.py.jinja
ai_bootstrap/templates/core_langchain/copier.yml
ai_bootstrap/templates/core_langchain/requirements.txt.jinja
ai_bootstrap/templates/core_langchain/.devcontainer/devcontainer.json.jinja
ai_bootstrap/templates/core_langchain/notebooks/example_usage.ipynb.jinja
ai_bootstrap/templates/core_langchain/src/__init__.py
ai_bootstrap/templates/core_langchain/src/config.py.jinja
ai_bootstrap/templates/core_langchain/src/main.py.jinja
ai_bootstrap/templates/core_langchain/src/chains/__init__.py
ai_bootstrap/templates/core_langchain/src/chains/custom_chains.py.jinja
ai_bootstrap/templates/core_langchain/src/llms/__init__.py
ai_bootstrap/templates/core_langchain/src/llms/providers.py.jinja
ai_bootstrap/templates/core_langchain/src/prompts/__init__.py
ai_bootstrap/templates/core_langchain/src/prompts/templates.py.jinja
ai_bootstrap/templates/core_langchain/src/tools/__init__.py
ai_bootstrap/templates/core_langchain/src/tools/custom_tools.py.jinja
ai_bootstrap/templates/core_langchain/tests/__init__.py
ai_bootstrap/templates/core_langchain/tests/test_chains.py.jinja
ai_bootstrap/templates/multi_agent_system/.env.example
ai_bootstrap/templates/multi_agent_system/.gitignore
ai_bootstrap/templates/multi_agent_system/README.md.jinja
ai_bootstrap/templates/multi_agent_system/app.py.jinja
ai_bootstrap-2.2.0.dist-info/METADATA
ai_bootstrap-2.2.0.dist-info/WHEEL
ai_bootstrap-2.2.0.dist-info/entry_points.txt
ai_bootstrap-2.2.0.dist-info/RECORD
