Metadata-Version: 2.4
Name: ai-bootstrap
Version: 2.2.0
Summary: AI-powered project scaffolding with requirement analysis
Project-URL: Homepage, https://github.com/yourusername/ai-bootstrap
Author-email: Soham Chaudhari <sohamrc0@gmail.com>
License: MIT
Requires-Python: >=3.9
Requires-Dist: anthropic
Requires-Dist: asyncio
Requires-Dist: copier
Requires-Dist: jinja2
Requires-Dist: langchain-anthropic
Requires-Dist: langchain-community
Requires-Dist: langchain-core
Requires-Dist: langchain-mistralai
Requires-Dist: langchain-openai
Requires-Dist: nest-asyncio
Requires-Dist: openai
Requires-Dist: pydantic
Requires-Dist: pydantic-settings
Requires-Dist: python-dotenv
Requires-Dist: pyyaml
Requires-Dist: rich
Requires-Dist: typer[all]
